s3_cargo/__init__.py
s3_cargo/cargoconf.py
s3_cargo/cargomain.py
s3_cargo/msgformat.py
s3_cargo-2022.2.dist-info/LICENSE
s3_cargo-2022.2.dist-info/WHEEL
s3_cargo-2022.2.dist-info/METADATA
s3_cargo-2022.2.dist-info/RECORD
