Metadata-Version: 2.1
Name: s3-cargo
Version: 2022.2
Summary: Manage your projects in S3 buckets.
License: AGPL
Author: MONTANA Knowledge Management ltd.
Author-email: info@distiller.dev
Requires-Python: >=3.8,<3.10
Classifier: License :: Other/Proprietary License
Classifier: Programming Language :: Python :: 3
Classifier: Programming Language :: Python :: 3.8
Classifier: Programming Language :: Python :: 3.9
Provides-Extra: dev_tools
Requires-Dist: PyYAML (>=6.0,<7.0)
Requires-Dist: boto3 (>=1.20.49,<2.0.0)
Requires-Dist: mkdocs (>=1.2.3,<2.0.0)
Requires-Dist: mkdocs-git-revision-date-plugin (>=0.3.1,<0.4.0)
Requires-Dist: mkdocs-material (>7.3)
Requires-Dist: mkdocstrings (>0.16.0)
Requires-Dist: patool (>=1.12,<2.0)
Requires-Dist: pudb (>=2022.1,<2023.0); extra == "dev_tools"
Requires-Dist: pydantic (>=1.9.0,<2.0.0)
Requires-Dist: pyunpack (>=0.2.2,<0.3.0)
